Grammaticomastix-0.0.1rc12.dist-info/DESCRIPTION.rst
Grammaticomastix-0.0.1rc12.dist-info/METADATA
Grammaticomastix-0.0.1rc12.dist-info/RECORD
Grammaticomastix-0.0.1rc12.dist-info/WHEEL
Grammaticomastix-0.0.1rc12.dist-info/entry_points.txt
Grammaticomastix-0.0.1rc12.dist-info/metadata.json
Grammaticomastix-0.0.1rc12.dist-info/top_level.txt
dchars/__init__.py
dchars/config_ini.py
dchars/config_ini_data.py
dchars/dcharacter.py
dchars/dchars.py
dchars/dstring.py
dchars/languages_name.py
dchars/successivetransformations.py
dchars/errors/__init__.py
dchars/errors/errors.py
dchars/languages/__init__.py
dchars/languages/ang/__init__.py
dchars/languages/ang/dcharacter.py
dchars/languages/ang/dstring.py
dchars/languages/ang/symbols.py
dchars/languages/ang/transliterations/__init__.py
dchars/languages/ang/transliterations/basic/__init__.py
dchars/languages/ang/transliterations/basic/basic.py
dchars/languages/ang/transliterations/basic/ucombinations.py
dchars/languages/bod/__init__.py
dchars/languages/bod/buffer.py
dchars/languages/bod/dcharacter.py
dchars/languages/bod/dstring.py
dchars/languages/bod/internalstructure.py
dchars/languages/bod/sorting_methods_tables.py
dchars/languages/bod/syllabic_structure.py
dchars/languages/bod/symbols.py
dchars/languages/bod/transliterations/__init__.py
dchars/languages/bod/transliterations/bodsan/__init__.py
dchars/languages/bod/transliterations/bodsan/bodsan.py
dchars/languages/bod/transliterations/bodsan/bodsan_symbols.py
dchars/languages/bod/transliterations/ewts/__init__.py
dchars/languages/bod/transliterations/ewts/ewts.py
dchars/languages/bod/transliterations/ewts/ewts_buffer.py
dchars/languages/bod/transliterations/ewts/ewts_symbols.py
dchars/languages/bod/transliterations/ewts/ucombinations.py
dchars/languages/fro/__init__.py
dchars/languages/fro/dcharacter.py
dchars/languages/fro/dstring.py
dchars/languages/fro/symbols.py
dchars/languages/fro/transliterations/__init__.py
dchars/languages/fro/transliterations/basic/__init__.py
dchars/languages/fro/transliterations/basic/basic.py
dchars/languages/fro/transliterations/basic/ucombinations.py
dchars/languages/grc/__init__.py
dchars/languages/grc/dcharacter.py
dchars/languages/grc/dstring.py
dchars/languages/grc/symbols.py
dchars/languages/grc/transliterations/__init__.py
