Metadata-Version: 2.0
Name: Grammaticomastix
Version: 0.0.1rc12
Summary: Insert and update blocks of text into text files
Home-page: https://github.com/suizokukan/grammaticomastix
Author: Xavier Faure (suizokukan / 94.23.197.37)
Author-email: suizokukan@orange.fr
License: GPL-3.0
Keywords: file manager tags
Platform: UNKNOWN
Classifier: Development Status :: 2 - Pre-Alpha
Classifier: Intended Audience :: End Users/Desktop
Classifier: Topic :: Utilities
Classifier: License :: OSI Approved :: GNU General Public License v3 (GPLv3)
Classifier: Programming Language :: Python :: 3
